{
    "name": "animation_spear2",
    "author": "",
    "description": "", 
    "emote":{
        "isLoop": "false",
        "returnTick": 0,
        "beginTick":0,
        "endTick":20,
        "stopTick":30,
        "degrees":false,
        "moves":[
            
            {
                "tick":5,
                "easing": "EASEINOUTQUAD",
                "turn": 0,
                "head":{
                    "y":-0.0
                }
            },
            {
                "tick":5,
                "easing": "EASEINOUTQUAD",
                "turn": 0,
                "head":{
                    "z":-0.0
                }
            },
            {
                "tick":5,
                "easing": "EASEINOUTQUAD",
                "turn": 0,
                "head":{
                    "x":-0.0
                }
            },
            {
                "tick":5,
                "easing": "EASEINOUTQUAD",
                "turn": 0,
                "head":{
                    "yaw":0.6426584124565125
                }
            },
            {
                "tick":10,
                "easing": "EASEINOUTQUAD",
                "turn": 0,
                "head":{
                    "yaw":-0.2991158366203308
                }
            },
            {
                "tick":5,
                "easing": "EASEINOUTQUAD",
                "turn": 0,
                "head":{
                    "roll":-0.0
                }
            },
            {
                "tick":10,
                "easing": "EASEINOUTQUAD",
                "turn": 0,
                "head":{
                    "roll":-0.025766711682081223
                }
            },
            {
                "tick":5,
                "easing": "EASEINOUTQUAD",
                "turn": 0,
                "head":{
                    "pitch":-0.0
                }
            },
            {
                "tick":10,
                "easing": "EASEINOUTQUAD",
                "turn": 0,
                "head":{
                    "pitch":-0.07413264364004135
                }
            },
            {
                "tick":5,
                "easing": "EASEINOUTQUAD",
                "turn": 0,
                "torso":{
                    "yaw":0.8946384787559509
                }
            },
            {
                "tick":10,
                "easing": "EASEINOUTQUAD",
                "turn": 0,
                "torso":{
                    "yaw":-0.7398695945739746
                }
            },
            {
                "tick":5,
                "easing": "EASEINOUTQUAD",
                "turn": 0,
                "torso":{
                    "roll":-0.0
                }
            },
            {
                "tick":5,
                "easing": "EASEINOUTQUAD",
                "turn": 0,
                "torso":{
                    "pitch":0.0
                }
            },
            {
                "tick":5,
                "easing": "EASEINOUTQUAD",
                "turn": 0,
                "torso":{
                    "y":0.0
                }
            },
            {
                "tick":5,
                "easing": "EASEINOUTQUAD",
                "turn": 0,
                "torso":{
                    "x":0.0
                }
            },
            {
                "tick":5,
                "easing": "EASEINOUTQUAD",
                "turn": 0,
                "torso":{
                    "z":-0.0
                }
            },
            {
                "tick":10,
                "easing": "EASEINOUTQUAD",
                "turn": 0,
                "torso":{
                    "bend":0.07214013487100601
                }
            },
            {
                "tick":5,
                "easing": "EASEINOUTQUAD",
                "turn": 0,
                "rightArm":{
                    "yaw":-0.3749864399433136
                }
            },
            {
                "tick":5,
                "easing": "EASEINOUTQUAD",
                "turn": 0,
                "rightArm":{
                    "roll":0.325903981924057
                }
            },
            {
                "tick":5,
                "easing": "EASEINOUTQUAD",
                "turn": 0,
                "rightArm":{
                    "pitch":-1.8587342500686646
                }
            },
            {
                "tick":5,
                "easing": "EASEINOUTQUAD",
                "turn": 0,
                "rightArm":{
                    "bend":-0.6406983733177185
                }
            },
            {
                "tick":10,
                "easing": "EASEINOUTQUAD",
                "turn": 0,
                "rightArm":{
                    "bend":-0.6325353980064392
                }
            },
            {
                "tick":5,
                "easing": "EASEINOUTQUAD",
                "turn": 0,
                "leftArm":{
                    "roll":-1.8420227766036987
                }
            },
            {
                "tick":5,
                "easing": "EASEINOUTQUAD",
                "turn": 0,
                "leftArm":{
                    "yaw":-0.11730357259511948
                }
            },
            {
                "tick":5,
                "easing": "EASEINOUTQUAD",
                "turn": 0,
                "leftArm":{
                    "pitch":-0.9760188460350037
                }
            },
            {
                "tick":5,
                "easing": "EASEINOUTQUAD",
                "turn": 0,
                "leftArm":{
                    "bend":-0.202969029545784
                }
            },
            {
                "tick":5,
                "easing": "EASEINOUTQUAD",
                "turn": 0,
                "rightLeg":{
                    "yaw":0.002632390707731247
                }
            },
            {
                "tick":10,
                "easing": "EASEINOUTQUAD",
                "turn": 0,
                "rightLeg":{
                    "yaw":-0.04092080518603325
                }
            },
            {
                "tick":5,
                "easing": "EASEINOUTQUAD",
                "turn": 0,
                "rightLeg":{
                    "roll":0.15549398958683014
                }
            },
            {
                "tick":10,
                "easing": "EASEINOUTQUAD",
                "turn": 0,
                "rightLeg":{
                    "roll":0.17753979563713074
                }
            },
            {
                "tick":5,
                "easing": "EASEINOUTQUAD",
                "turn": 0,
                "rightLeg":{
                    "pitch":-0.2975505590438843
                }
            },
            {
                "tick":10,
                "easing": "EASEINOUTQUAD",
                "turn": 0,
                "rightLeg":{
                    "pitch":0.2659929692745209
                }
            },
            {
                "tick":10,
                "easing": "EASEINOUTQUAD",
                "turn": 0,
                "rightLeg":{
                    "bend":-0.21732299029827118
                }
            },
            {
                "tick":5,
                "easing": "EASEINOUTQUAD",
                "turn": 0,
                "leftLeg":{
                    "yaw":0.004466816782951355
                }
            },
            {
                "tick":10,
                "easing": "EASEINOUTQUAD",
                "turn": 0,
                "leftLeg":{
                    "yaw":-0.14660732448101044
                }
            },
            {
                "tick":5,
                "easing": "EASEINOUTQUAD",
                "turn": 0,
                "leftLeg":{
                    "roll":-0.10547532141208649
                }
            },
            {
                "tick":10,
                "easing": "EASEINOUTQUAD",
                "turn": 0,
                "leftLeg":{
                    "roll":-0.31254711747169495
                }
            },
            {
                "tick":5,
                "easing": "EASEINOUTQUAD",
                "turn": 0,
                "leftLeg":{
                    "pitch":0.08456957340240479
                }
            },
            {
                "tick":10,
                "easing": "EASEINOUTQUAD",
                "turn": 0,
                "leftLeg":{
                    "pitch":-0.1194138452410698
                }
            },
            {
                "tick":5,
                "easing": "EASEINOUTQUAD",
                "turn": 0,
                "leftLeg":{
                    "y":12.0
                }
            },
            {
                "tick":5,
                "easing": "EASEINOUTQUAD",
                "turn": 0,
                "leftLeg":{
                    "z":-0.1
                }
            },
            {
                "tick":5,
                "easing": "EASEINOUTQUAD",
                "turn": 0,
                "leftLeg":{
                    "x":1.9
                }
            },
            {
                "tick":10,
                "easing": "EASEINOUTQUAD",
                "turn": 0,
                "leftLeg":{
                    "bend":-0.0
                }
            },
            {
                "tick":5,
                "easing": "EASEINOUTQUAD",
                "turn": 0,
                "leftItem":{
                    "roll":1.4561798572540283
                }
            },
            {
                "tick":10,
                "easing": "EASEINOUTQUAD",
                "turn": 0,
                "leftItem":{
                    "roll":2.2431468963623047
                }
            },
            {
                "tick":5,
                "easing": "EASEINOUTQUAD",
                "turn": 0,
                "leftItem":{
                    "x":-1.2977651357650757
                }
            },
            {
                "tick":10,
                "easing": "EASEINOUTQUAD",
                "turn": 0,
                "leftItem":{
                    "x":0.7948665022850037
                }
            },
            {
                "tick":5,
                "easing": "EASEINOUTQUAD",
                "turn": 0,
                "leftItem":{
                    "y":-0.05788087844848633
                }
            },
            {
                "tick":10,
                "easing": "EASEINOUTQUAD",
                "turn": 0,
                "leftItem":{
                    "y":0.471365362405777
                }
            },
            {
                "tick":5,
                "easing": "EASEINOUTQUAD",
                "turn": 0,
                "leftItem":{
                    "z":-1.1838867664337158
                }
            },
            {
                "tick":10,
                "easing": "EASEINOUTQUAD",
                "turn": 0,
                "leftItem":{
                    "z":-3.1201581954956055
                }
            },
            {
                "tick":5,
                "easing": "EASEINOUTQUAD",
                "turn": 0,
                "leftItem":{
                    "pitch":-0.9336533546447754
                }
            },
            {
                "tick":10,
                "easing": "EASEINOUTQUAD",
                "turn": 0,
                "leftItem":{
                    "pitch":-1.62204110622406
                }
            },
            {
                "tick":5,
                "easing": "EASEINOUTQUAD",
                "turn": 0,
                "leftItem":{
                    "yaw":-1.2148635387420654
                }
            },
            {
                "tick":10,
                "easing": "EASEINOUTQUAD",
                "turn": 0,
                "leftItem":{
                    "yaw":-0.2212594598531723
                }
            }
        ]
    }
}