{
    "name": "animation_double_edged_3",
    "author": "",
    "description": "", 
    "emote":{
        "isLoop": "false",
        "returnTick": 0,
        "beginTick":10,
        "endTick":20,
        "stopTick":30,
        "degrees":false,
        "moves":[
            
            {
                "tick":2,
                "easing": "EASEINOUTQUAD",
                "turn": 0,
                "head":{
                    "yaw":-0.02201893925666809
                }
            },
            {
                "tick":7,
                "easing": "EASEINOUTQUAD",
                "turn": 0,
                "head":{
                    "yaw":1.1247012615203857
                }
            },
            {
                "tick":2,
                "easing": "EASEINOUTQUAD",
                "turn": 0,
                "head":{
                    "roll":0.019248513504862785
                }
            },
            {
                "tick":7,
                "easing": "EASEINOUTQUAD",
                "turn": 0,
                "head":{
                    "roll":-0.003240330144762993
                }
            },
            {
                "tick":2,
                "easing": "EASEINOUTQUAD",
                "turn": 0,
                "head":{
                    "pitch":0.07767146080732346
                }
            },
            {
                "tick":7,
                "easing": "EASEINOUTQUAD",
                "turn": 0,
                "head":{
                    "pitch":0.14013245701789856
                }
            },
            {
                "tick":2,
                "easing": "EASEINOUTQUAD",
                "turn": 0,
                "torso":{
                    "yaw":-0.49158385396003723
                }
            },
            {
                "tick":7,
                "easing": "EASEINOUTQUAD",
                "turn": 0,
                "torso":{
                    "yaw":0.8195518851280212
                }
            },
            {
                "tick":10,
                "easing": "EASEINOUTQUAD",
                "turn": 0,
                "torso":{
                    "yaw":0.8096054792404175
                }
            },
            {
                "tick":2,
                "easing": "EASEINOUTQUAD",
                "turn": 0,
                "torso":{
                    "roll":0.0057598864659667015
                }
            },
            {
                "tick":7,
                "easing": "EASEINOUTQUAD",
                "turn": 0,
                "torso":{
                    "roll":0.006890926510095596
                }
            },
            {
                "tick":10,
                "easing": "EASEINOUTQUAD",
                "turn": 0,
                "torso":{
                    "roll":-0.14512920379638672
                }
            },
            {
                "tick":2,
                "easing": "EASEINOUTQUAD",
                "turn": 0,
                "torso":{
                    "pitch":-0.0116832060739398
                }
            },
            {
                "tick":7,
                "easing": "EASEINOUTQUAD",
                "turn": 0,
                "torso":{
                    "pitch":-0.00406252546235919
                }
            },
            {
                "tick":10,
                "easing": "EASEINOUTQUAD",
                "turn": 0,
                "torso":{
                    "pitch":-0.21268394589424133
                }
            },
            {
                "tick":10,
                "easing": "EASEINOUTQUAD",
                "turn": 0,
                "torso":{
                    "x":0.0
                }
            },
            {
                "tick":10,
                "easing": "EASEINOUTQUAD",
                "turn": 0,
                "torso":{
                    "z":-0.06965675950050354
                }
            },
            {
                "tick":10,
                "easing": "EASEINOUTQUAD",
                "turn": 0,
                "torso":{
                    "y":0.0
                }
            },
            {
                "tick":10,
                "easing": "EASEINOUTQUAD",
                "turn": 0,
                "torso":{
                    "bend":-0.10829968750476837
                }
            },
            {
                "tick":2,
                "easing": "EASEINOUTQUAD",
                "turn": 0,
                "rightArm":{
                    "yaw":-0.23709392547607422
                }
            },
            {
                "tick":7,
                "easing": "EASEINOUTQUAD",
                "turn": 0,
                "rightArm":{
                    "yaw":0.7241869568824768
                }
            },
            {
                "tick":2,
                "easing": "EASEINOUTQUAD",
                "turn": 0,
                "rightArm":{
                    "roll":0.03427295386791229
                }
            },
            {
                "tick":7,
                "easing": "EASEINOUTQUAD",
                "turn": 0,
                "rightArm":{
                    "roll":0.30049312114715576
                }
            },
            {
                "tick":2,
                "easing": "EASEINOUTQUAD",
                "turn": 0,
                "rightArm":{
                    "pitch":-0.5659178495407104
                }
            },
            {
                "tick":7,
                "easing": "EASEINOUTQUAD",
                "turn": 0,
                "rightArm":{
                    "pitch":-1.1718932390213013
                }
            },
            {
                "tick":2,
                "easing": "EASEINOUTQUAD",
                "turn": 0,
                "rightArm":{
                    "bend":-0.8988861441612244
                }
            },
            {
                "tick":7,
                "easing": "EASEINOUTQUAD",
                "turn": 0,
                "rightArm":{
                    "bend":-0.1600496917963028
                }
            },
            {
                "tick":7,
                "easing": "EASEINOUTQUAD",
                "turn": 0,
                "leftArm":{
                    "roll":-0.4316222071647644
                }
            },
            {
                "tick":7,
                "easing": "EASEINOUTQUAD",
                "turn": 0,
                "leftArm":{
                    "yaw":0.060522403568029404
                }
            },
            {
                "tick":7,
                "easing": "EASEINOUTQUAD",
                "turn": 0,
                "leftArm":{
                    "pitch":0.6259742975234985
                }
            },
            {
                "tick":7,
                "easing": "EASEINOUTQUAD",
                "turn": 0,
                "leftArm":{
                    "bend":-0.11630487442016602
                }
            },
            {
                "tick":2,
                "easing": "EASEINOUTQUAD",
                "turn": 0,
                "rightLeg":{
                    "yaw":-0.816662609577179
                }
            },
            {
                "tick":10,
                "easing": "EASEINOUTQUAD",
                "turn": 0,
                "rightLeg":{
                    "yaw":0.6768820881843567
                }
            },
            {
                "tick":2,
                "easing": "EASEINOUTQUAD",
                "turn": 0,
                "rightLeg":{
                    "roll":0.003111124038696289
                }
            },
            {
                "tick":10,
                "easing": "EASEINOUTQUAD",
                "turn": 0,
                "rightLeg":{
                    "roll":0.08702734112739563
                }
            },
            {
                "tick":2,
                "easing": "EASEINOUTQUAD",
                "turn": 0,
                "rightLeg":{
                    "pitch":0.19217678904533386
                }
            },
            {
                "tick":10,
                "easing": "EASEINOUTQUAD",
                "turn": 0,
                "rightLeg":{
                    "pitch":-0.7603116035461426
                }
            },
            {
                "tick":10,
                "easing": "EASEINOUTQUAD",
                "turn": 0,
                "rightLeg":{
                    "bend":0.7364615797996521
                }
            },
            {
                "tick":2,
                "easing": "EASEINOUTQUAD",
                "turn": 0,
                "leftLeg":{
                    "yaw":-0.4347750246524811
                }
            },
            {
                "tick":10,
                "easing": "EASEINOUTQUAD",
                "turn": 0,
                "leftLeg":{
                    "yaw":0.006075890734791756
                }
            },
            {
                "tick":2,
                "easing": "EASEINOUTQUAD",
                "turn": 0,
                "leftLeg":{
                    "roll":-0.08722285181283951
                }
            },
            {
                "tick":10,
                "easing": "EASEINOUTQUAD",
                "turn": 0,
                "leftLeg":{
                    "roll":-0.10813360661268234
                }
            },
            {
                "tick":2,
                "easing": "EASEINOUTQUAD",
                "turn": 0,
                "leftLeg":{
                    "pitch":0.09256298094987869
                }
            },
            {
                "tick":10,
                "easing": "EASEINOUTQUAD",
                "turn": 0,
                "leftLeg":{
                    "pitch":0.07985030114650726
                }
            },
            {
                "tick":7,
                "easing": "EASEINOUTQUAD",
                "turn": 0,
                "rightItem":{
                    "pitch":-0.9810270667076111
                }
            },
            {
                "tick":7,
                "easing": "EASEINOUTQUAD",
                "turn": 0,
                "rightItem":{
                    "yaw":-0.22604072093963623
                }
            },
            {
                "tick":7,
                "easing": "EASEINOUTQUAD",
                "turn": 0,
                "rightItem":{
                    "roll":-0.42928066849708557
                }
            }
        ]
    }
}